mushroom/__init__.py
mushroom/application.py
mushroom/http.py
mushroom/messaging.py
mushroom/server.py
mushroom/session.py
mushroom/simple.py
mushroom/transport.py
mushroom/utils.py
mushroom/django/__init__.py
mushroom/django/management.py
mushroom/django/methods.py
mushroom/django/middlewares.py
mushroom/django/views.py
mushroom/gunicorn/__init__.py
mushroom/gunicorn/workers.py
mushroom/rpc/__init__.py
mushroom/rpc/dispatcher.py
mushroom/rpc/engine.py
mushroom/rpc/exceptions.py
mushroom/rpc/messages.py
mushroom/rpc/methods.py
mushroom/rpc/middleware.py
mushroom/rpc/signals.py
mushroom-0.9.20.dist-info/DESCRIPTION.rst
mushroom-0.9.20.dist-info/METADATA
mushroom-0.9.20.dist-info/RECORD
mushroom-0.9.20.dist-info/WHEEL
mushroom-0.9.20.dist-info/metadata.json
mushroom-0.9.20.dist-info/top_level.txt
